yaep/__init__.py
yaep/exceptions.py
yaep/utils.py
yaep/version.py
yaep/yaep.py
yaep-0.0.6.dist-info/DESCRIPTION.rst
yaep-0.0.6.dist-info/METADATA
yaep-0.0.6.dist-info/RECORD
yaep-0.0.6.dist-info/WHEEL
yaep-0.0.6.dist-info/metadata.json
yaep-0.0.6.dist-info/top_level.txt
