Metadata-Version: 1.0
Name: yaep
Version: 0.0.6
Summary: YAEP - Yet Another Environment Package
Home-page: https://github.com/jimjkelly/yaep
Author: James Kelly
Author-email: pthread1981@gmail.com
License: ISC
Platform: UNKNOWN
